casscache.py
casscache-0.1.1.dist-info/DESCRIPTION.rst
casscache-0.1.1.dist-info/METADATA
casscache-0.1.1.dist-info/pydist.json
casscache-0.1.1.dist-info/RECORD
casscache-0.1.1.dist-info/top_level.txt
casscache-0.1.1.dist-info/WHEEL
casscache-0.1.1.dist-info/zip-safe
