Metadata-Version: 2.0
Name: casscache
Version: 0.1.1
Summary: Casscache is a python-memcached compatible API for interfacing with Cassandra
Home-page: https://github.com/mattrobenolt/python-casscache
Author: Matt Robenolt
Author-email: matt@ydekproductions.com
License: BSD
Platform: UNKNOWN
Classifier: Development Status :: 4 - Beta
Classifier: Intended Audience :: Developers
Classifier: Operating System :: OS Independent
Classifier: Topic :: Software Development
Requires-Dist: cassandra-driver
